ml_metadata/__init__.py
ml_metadata/version.py
ml_metadata/metadata_store/__init__.py
ml_metadata/metadata_store/_pywrap_tf_metadata_store_serialized.so
ml_metadata/metadata_store/metadata_store.py
ml_metadata/metadata_store/metadata_store_test.py
ml_metadata/metadata_store/pywrap_tf_metadata_store_serialized.py
ml_metadata/metadata_store/types.py
ml_metadata/metadata_store/types_test.py
ml_metadata/proto/__init__.py
ml_metadata/proto/metadata_store_pb2.py
ml_metadata/proto/metadata_store_service_pb2.py
ml_metadata/proto/metadata_store_service_pb2_grpc.py
bmlx_metadata-1.0.4.dist-info/LICENSE
bmlx_metadata-1.0.4.dist-info/METADATA
bmlx_metadata-1.0.4.dist-info/WHEEL
bmlx_metadata-1.0.4.dist-info/namespace_packages.txt
bmlx_metadata-1.0.4.dist-info/top_level.txt
bmlx_metadata-1.0.4.dist-info/RECORD
